{
  "version": "6",
  "dialect": "sqlite",
  "id": "9d0f02bc-a238-480d-8078-4dfcfdc94819",
  "prevId": "0746df7c-7624-4b14-936d-6ca1dba7dd5b",
  "tables": {
    "games_table": {
      "name": "games_table",
      "columns": {
        "id": {
          "name": "id",
          "type": "text(4)",
          "primaryKey": true,
          "notNull": true,
          "autoincrement": false,
          "default": "'XWU9'"
        },
        "pass": {
          "name": "pass",
          "type": "text",
          "primaryKey": false,
          "notNull": true,
          "autoincrement": false
        },
        "players": {
          "name": "players",
          "type": "text",
          "primaryKey": false,
          "notNull": false,
          "autoincrement": false
        },
        "questions": {
          "name": "questions",
          "type": "text",
          "primaryKey": false,
          "notNull": false,
          "autoincrement": false
        }
      },
      "indexes": {},
      "foreignKeys": {},
      "compositePrimaryKeys": {},
      "uniqueConstraints": {},
      "checkConstraints": {}
    }
  },
  "views": {},
  "enums": {},
  "_meta": {
    "schemas": {},
    "tables": {},
    "columns": {}
  },
  "internal": {
    "indexes": {}
  }
}